<?xml version="1.0" encoding="UTF-8"?>
<comment version="3.0">
  <caption>Panasonic, DMC-TZ61, f/6.1, ISO 100, 1/320 s</caption>
  <note>Nach Tauchgängen lassen Kormorane ihr Gefieder trocknen, Walchwil, Walchwil, 416 m</note>
  <place>Walchwil</place>
  <categories>
    <category value="DMC-TZ61"/>
    <category value="Fischreiher ( Ardea cinerea)"/>
    <category value="Graureiher"/>
    <category value="Kanton Zug"/>
    <category value="Panasonic"/>
    <category value="Switzerland"/>
    <category value="Tiere"/>
    <category value="Walchwil"/>
  </categories>
</comment>
